pyqualitas/__init__.py
pyqualitas/checks/__init__.py
pyqualitas/checks/arbitarychecks.py
pyqualitas/checks/dualdfchecks.py
pyqualitas/checks/singledfchecks.py
pyqualitas/checksuite/__init__.py
pyqualitas/checksuite/checksuite.py
pyqualitas/utils/__init__.py
pyqualitas/utils/helper.py
pyqualitas/utils/logger.py
pyqualitas/utils/template/TestResult.html
pyqualitas-2.0.1.dist-info/licenses/LICENSE
pyqualitas-2.0.1.dist-info/METADATA
pyqualitas-2.0.1.dist-info/WHEEL
pyqualitas-2.0.1.dist-info/top_level.txt
pyqualitas-2.0.1.dist-info/RECORD
