Metadata-Version: 2.4
Name: pyQualitas
Version: 2.0.1
Summary: A project to ensure the data quality using python
Home-page: https://github.com/IamVenkatesh/pyQuality/wiki
Author: Venkatesh Venkataramani
Author-email: venkatesh.venkataramani@gmail.com
Classifier: Programming Language :: Python :: 3.10
Classifier: License :: OSI Approved :: MIT License
Classifier: Operating System :: Unix
Classifier: Development Status :: 5 - Production/Stable
Classifier: Topic :: Software Development :: Quality Assurance
Classifier: Topic :: Software Development :: Testing
License-File: LICENSE
Requires-Dist: pyspark>=3.5.5
Requires-Dist: Jinja2>=3.1.6
Requires-Dist: pandas>=2.2.3
Requires-Dist: slack-sdk>=3.35.0
Requires-Dist: pymsteams>=0.2.5
Dynamic: author
Dynamic: author-email
Dynamic: classifier
Dynamic: description
Dynamic: description-content-type
Dynamic: home-page
Dynamic: license-file
Dynamic: requires-dist
Dynamic: summary
